modos_schema/_version.py
modos_schema/datamodel/__init__.py
modos_schema/datamodel/modos_schema.py
modos_schema/schema/modos_schema.yaml
modos_schema-0.3.4.dist-info/METADATA
modos_schema-0.3.4.dist-info/WHEEL
modos_schema-0.3.4.dist-info/licenses/LICENSE
modos_schema-0.3.4.dist-info/licenses/NOTICE
modos_schema-0.3.4.dist-info/RECORD
