Metadata-Version: 2.4
Name: modos_schema
Version: 0.3.4
Summary: Metadata schema for the Multi-Omics Digital Object System
License: Apache-2.0
License-File: LICENSE
License-File: NOTICE
Author: Cyril Matthey-Doret
Requires-Python: >=3.10,<4.0
Classifier: License :: OSI Approved :: Apache Software License
Classifier: Programming Language :: Python :: 3
Classifier: Programming Language :: Python :: 3.10
Classifier: Programming Language :: Python :: 3.11
Classifier: Programming Language :: Python :: 3.12
Classifier: Programming Language :: Python :: 3.13
Classifier: Programming Language :: Python :: 3.14
Provides-Extra: docs
Requires-Dist: linkml-runtime (>=1.9.1,<2.0.0)
